selenium_remote/__init__.py
selenium_remote/main.py
selenium_remote-0.1.5.dist-info/LICENSE
selenium_remote-0.1.5.dist-info/METADATA
selenium_remote-0.1.5.dist-info/WHEEL
selenium_remote-0.1.5.dist-info/RECORD
